threadedcomments/__init__.py
threadedcomments/admin.py
threadedcomments/forms.py
threadedcomments/models.py
threadedcomments/tests.py
threadedcomments/util.py
threadedcomments/fixtures/simple_tree.json
threadedcomments/management/__init__.py
threadedcomments/management/commands/__init__.py
threadedcomments/management/commands/migrate_comments.py
threadedcomments/management/commands/migrate_threaded_comments.py
threadedcomments/migrations/0001_initial.py
threadedcomments/migrations/0002_auto_20150521_2011.py
threadedcomments/migrations/0003_threadedcomment_newest_activity.py
threadedcomments/migrations/__init__.py
threadedcomments/sql/threadedcomment.mysql.sql
threadedcomments/templates/sample_tree.html
threadedcomments/templates/comments/list.html
threadedcomments/templatetags/__init__.py
threadedcomments/templatetags/threadedcomments_tags.py
django_threadedcomments-2.0.dist-info/AUTHORS.rst
django_threadedcomments-2.0.dist-info/LICENSE.txt
django_threadedcomments-2.0.dist-info/METADATA
django_threadedcomments-2.0.dist-info/WHEEL
django_threadedcomments-2.0.dist-info/top_level.txt
django_threadedcomments-2.0.dist-info/RECORD
