Metadata-Version: 2.1
Name: django-threadedcomments
Version: 2.0
Summary: A simple yet flexible threaded commenting system.
Home-page: https://github.com/HonzaKral/django-threadedcomments
Author: Eric Florenzano
Author-email: floguy@gmail.com
Maintainer: Diederik van der Boor
Maintainer-email: vdboor@edoburu.nl
License: BSD
Download-URL: https://github.com/HonzaKral/django-threadedcomments/zipball/master
Keywords: django,comments,threading
Platform: UNKNOWN
Classifier: Development Status :: 4 - Beta
Classifier: Environment :: Web Environment
Classifier: Framework :: Django
Classifier: Intended Audience :: Developers
Classifier: License :: OSI Approved :: BSD License
Classifier: Operating System :: OS Independent
Classifier: Programming Language :: Python
Classifier: Programming Language :: Python :: 2.7
Classifier: Programming Language :: Python :: 3
Classifier: Programming Language :: Python :: 3.4
Classifier: Programming Language :: Python :: 3.5
Classifier: Programming Language :: Python :: 3.6
Classifier: Framework :: Django
Classifier: Framework :: Django :: 1.11
Classifier: Framework :: Django :: 2.0
Classifier: Framework :: Django :: 2.1
Classifier: Topic :: Internet :: WWW/HTTP
Classifier: Topic :: Internet :: WWW/HTTP :: Dynamic Content
Classifier: Topic :: Software Development :: Libraries :: Python Modules
Requires-Dist: django-contrib-comments (>=1.9.0)
